{
  "id": "20260208_005444_7bff",
  "estado": "validada",
  "dedup_key": "F:|DX:esclerosis múltipe. variante evolutiva a recaídas y remisiones (oms: 340). fecha de diagnóstico: abril/mayo de 1999. comentarios: debe continuar sin interrupción, con la terapia inmunomoduladora, con muy buena tolerancia y eficacia hasta la fecha; cuyo objetivo es disminuir el número y la gravedad de las recaídas, así como la cantidad de internaciones y la terapia inmunosupresora más agresiva, retrasando la discapacidad acumulativa y previniendo la atrofia cerebral. por lo cual se solicita continuidad para rebif: 3 jeringas prellenadas semanales, es decir 12 jeringas prellenadas de 44mcgr.=12mui c/u) c/28 días. fecha de inicio de rebif: septiembre 2004. por ninguna razón debe discontinuarse su administración pues se correrían riesgos de recaídas con las consecuencias que estas originan (a veces irreparables), debe administrarse hasta que aparezca una terapia superior o efectos adversos insostenibles. bibliografía respaldatoria: (rebif) - prisms 2 años. lancet 1998; 352: 1498-1504. - prisms 4 años. neurology 2001; 56: 1628-1636. - incomin neurology 2001; vol.248: supl.3 / vol.56: supl.2. - owims neurology 1999; 53: 679-686. - evidence. neurology 2002; 59: 1496-1506. - revista neurológica argentina 2000; 25: 142-145. ( - medicina (buenos aires) 2001; 61:470-480. es un medicamento con cobertura 100% a cargo de la obra social, de acuerdo al boletín oficial n° 30.089, 1ra. sección, página 8 del jueves 13 de febrero de 2003 del plan médico obligatorio (o administración de programas especiales) donde rebif figura expresamente. se trata además de un medicamento aprobado por la fda de los eeuu y el anmat en la argentina con esta precisa indicación. debido a cierta requisitoria quiero dejar bien en claro, sin embargo, que el número de brotes no deben ser limitantes en la provisión de la terapia, dichos criterios simplemente fueron utilizados en los diseños de ensayos terapéuticos y no debieran trasladarse a la clínica diaria sin entender de cada caso particular. además son criterios de ingreso a la terapia pero de ninguna manera de continuidad de la misma, pues si los brotes se continuarán igual al periodo pre-tratamiento solo reflejarían la ineficacia del mismo, es evidente que existe aun una gran confusión y errónea interpretación de la literatura, además les sugiero remitirse al consenso argentino sobre el uso de drogas inmunomoduladora en em apartado nº10 que es muy claro al respecto(() y si persistieran aun controversias no dude en comunicarse con este centro especializado en enfermedades desmielinizantes (único referente del ministerio de salud de la provincia de bs. as.). solicito: rebif (interferón-b.1ar), a una dosis de12 jeringas prellenadas de 12mui (44mcgrs.) c/28días. -unica dosificación posible- (no existen dos genéricos de este producto por lo que no puede ser cambiado o sustituido por otro nombre comercial distinto al rebif). ruego se respete la precisa indicación del médico tratante. atte. dr. santiago a. vétere|H:3073b7148e",
  "borrador": {
    "estado": "Procesado",
    "fuente": {
      "tipo": "DOC (Legacy)",
      "nombre_archivo": "historia_20260208_005444_7bff.doc"
    },
    "paciente": {
      "nombre": "Ana Carolina, Battista",
      "dni": null,
      "fecha_nacimiento": "1982-04-02",
      "obra_social": "IOMA",
      "nro_afiliado": "1262506611/01"
    },
    "consulta": {
      "fecha": null,
      "medico": null
    },
    "enfermedad": {
      "diagnostico": "ESCLEROSIS MÚLTIPE. Variante evolutiva a recaídas y remisiones (OMS: 340). Fecha de diagnóstico: Abril/mayo de 1999. Comentarios: Debe continuar sin interrupción, con la terapia inmunomoduladora, con muy buena tolerancia y eficacia hasta la fecha; cuyo objetivo es disminuir el número y la gravedad de las recaídas, así como la cantidad de internaciones y la terapia inmunosupresora más agresiva, retrasando la discapacidad acumulativa y previniendo la atrofia cerebral. Por lo cual se solicita continuidad para Rebif: 3 jeringas prellenadas semanales, es decir 12 jeringas prellenadas de 44Mcgr.=12MUI c/u) c/28 días. Fecha de inicio de Rebif: Septiembre 2004. Por ninguna razón debe discontinuarse su administración pues se correrían riesgos de recaídas con las consecuencias que estas originan (a veces irreparables), debe administrarse hasta que aparezca una terapia superior o efectos adversos insostenibles. Bibliografía respaldatoria: (Rebif) - PRISMS 2 años. Lancet 1998; 352: 1498-1504. - PRISMS 4 años. Neurology 2001; 56: 1628-1636. - INCOMIN Neurology 2001; vol.248: supl.3 / vol.56: supl.2. - OWIMS Neurology 1999; 53: 679-686. - EVIDENCE. Neurology 2002; 59: 1496-1506. - Revista Neurológica Argentina 2000; 25: 142-145. ( - Medicina (Buenos Aires) 2001; 61:470-480. Es un medicamento con cobertura 100% a cargo de la Obra Social, de acuerdo al Boletín Oficial N° 30.089, 1ra. Sección, página 8 del jueves 13 de febrero de 2003 del Plan Médico Obligatorio (o Administración de Programas Especiales) donde Rebif figura expresamente. Se trata además de un medicamento aprobado por la FDA de los EEUU y el ANMAT en la Argentina con esta precisa indicación. Debido a cierta requisitoria quiero dejar bien en claro, sin embargo, que el número de brotes no deben ser limitantes en la provisión de la terapia, dichos criterios simplemente fueron utilizados en los diseños de ensayos terapéuticos y no debieran trasladarse a la clínica diaria sin entender de cada caso particular. Además son criterios de ingreso a la terapia pero de ninguna manera de continuidad de la misma, pues si los brotes se continuarán igual al periodo pre-tratamiento solo reflejarían la ineficacia del mismo, es evidente que existe aun una gran confusión y errónea interpretación de la literatura, además les sugiero remitirse al Consenso Argentino sobre el uso de drogas Inmunomoduladora en EM apartado nº10 que es muy claro al respecto(() y si persistieran aun controversias no dude en comunicarse con este Centro Especializado en Enfermedades Desmielinizantes (único referente del Ministerio de Salud de la Provincia de Bs. As.). Solicito: REBIF (Interferón-B.1ar), a una dosis de12 jeringas prellenadas de 12MUI (44Mcgrs.) c/28días. -UNICA DOSIFICACIÓN POSIBLE- (No existen dos genéricos de este producto por lo que no puede ser cambiado o sustituido por otro nombre comercial distinto al Rebif). Ruego se respete la precisa indicación del médico tratante. Atte. Dr. Santiago A. Vétere",
      "codigo": "G35",
      "forma": "RR",
      "fecha_inicio": "1998-04-02",
      "edss": null
    },
    "complementarios": {
      "rmn": [
        {
          "fecha": null,
          "actividad": null,
          "gd": null,
          "regiones": [
            "periventricular"
          ]
        }
      ],
      "puncion_lumbar": {
        "realizada": false,
        "bandas": null
      }
    },
    "tratamientos": [
      {
        "molecula": "Interferón Beta-1a",
        "droga": "Interferón Beta-1a",
        "dosis": "44 Mcg",
        "frecuencia": "Semanal",
        "estado": "Activo",
        "inicio": null
      },
      {
        "molecula": "Interferón",
        "droga": "Interferón",
        "dosis": "44 Mcg",
        "frecuencia": null,
        "estado": "Activo",
        "inicio": null
      }
    ],
    "secciones_texto": {
      "sintomas_principales": "Obra Social: IOMA Nº de afiliado: 1262506611/01 Inicio de la afección: 2 de abril de 1998 Asistido en este servicio desde: 16 de marzo de 1999 principales: en un curso de brotes y remisiones, múltiples síntomas compatibles con afección de la sustancia blanca del sistema nervioso central, como: parestesias e hipoestesias de miembros, disminución de la fuerza con torpeza motora y dificultades para la marcha, trastornos en el equilibrio y coordinación, fallas en los esfínteres con episódica urgencia urinaria y constipación creciente, compromiso de pares craneanos (segundo, quinto, y sexto par a derecha).Últimas recaídas: -Septiembre 2004: hemiparesia derecha +diplopia; -Enero de 2005: compromiso crural izquierdo leve",
      "antecedentes": "",
      "examen_fisico": "Elementos de: - bipiramidalismo a predominio crural y derecho. - sensitivo-propioceptivo congruente. - atáxico axial y apendicular. - esfinteriano vesical eferente. - pares craneanos: II, V, VI a derecha",
      "agrupacion_sindromica": "",
      "comentario": "Debe continuar sin interrupción, con la terapia inmunomoduladora, con muy buena tolerancia y eficacia hasta la fecha; cuyo objetivo es disminuir el número y la gravedad de las recaídas, así como la cantidad de internaciones y la terapia inmunosupresora más agresiva, retrasando la discapacidad acumulativa y previniendo la atrofia cerebral\nPor lo cual se solicita continuidad para Rebif: 3 jeringas prellenadas semanales, es decir 12 jeringas prellenadas de 44Mcgr.=12MUI c/u) c/28 días\nFecha de inicio de Rebif: Septiembre 2004\nPor ninguna razón debe discontinuarse su administración pues se correrían riesgos de recaídas con las consecuencias que estas originan (a veces irreparables), debe administrarse hasta que aparezca una terapia superior o efectos adversos insostenibles",
      "estudios": "realizados: rutina completa de laboratorio, coagulograma, inmunocolagenograma (factor reumatoide, por RR., y p. de látex; células LE., Ac. anti-nuclares, Ac. anti-ADN y complementemia), determinación de TSH, T3, T4 y Ac. anti-tiroideos, hepatograma completo, serología para VIH, análisis de orina completa\nResultando todos los antes mencionados dentro de parámetros normales\nLas RMN. de cerebro muestran múltiples imágenes en la sustancia blanca del SNC: periventriculares, de extensa topografía, algunas con gran actividad, en el pasado(ver fotocopias de informes que se adjuntan)\nLos potenciales evocados SS. de miembros izquierdos mostraron demora en sus latencias",
      "evolucion": ""
    },
    "texto_original": " HOSPITAL INTERZONAL GENERAL DE AGUDOS “ Gral. SAN MARTIN” SERVICIO DE NEUROLOGÍA SECCIÓN DE ENFERMEDADES DESMIELINIZANTES URGENTE RESUMEN DE HISTORIA CLÍNICA La Plata, . Nombre y apellido: Ana Carolina, Battista. Fecha de Nacimiento: 02/04/82 Dirección: 74 nº 675 Dto. 3. La Plata. Teléfono: 453-5360. Obra Social: IOMA Nº de afiliado: 1262506611/01 Inicio de la afección: 2 de abril de 1998 Asistido en este servicio desde: 16 de marzo de 1999 Síntomas principales: en un curso de brotes y remisiones, múltiples síntomas compatibles con afección de la sustancia blanca del sistema nervioso central, como: parestesias e hipoestesias de miembros, disminución de la fuerza con torpeza motora y dificultades para la marcha, trastornos en el equilibrio y coordinación, fallas en los esfínteres con episódica urgencia urinaria y constipación creciente, compromiso de pares craneanos (segundo, quinto, y sexto par a derecha).Últimas recaídas: -Septiembre 2004: hemiparesia derecha +diplopia; -Enero de 2005: compromiso crural izquierdo leve. Rasgos semiológicos: Elementos de: - bipiramidalismo a predominio crural y derecho. - sensitivo-propioceptivo congruente. - atáxico axial y apendicular. - esfinteriano vesical eferente. - pares craneanos: II, V, VI a derecha. Estudios realizados: rutina completa de laboratorio, coagulograma, inmunocolagenograma (factor reumatoide, por RR., y p. de látex; células LE., Ac. anti-nuclares, Ac. anti-ADN y complementemia), determinación de TSH, T3, T4 y Ac. anti-tiroideos, hepatograma completo, serología para VIH, análisis de orina completa. Resultando todos los antes mencionados dentro de parámetros normales. Las RMN. de cerebro muestran múltiples imágenes en la sustancia blanca del SNC: periventriculares, de extensa topografía, algunas con gran actividad, en el pasado(ver fotocopias de informes que se adjuntan). Los potenciales evocados SS. de miembros izquierdos mostraron demora en sus latencias. Diagnóstico: ESCLEROSIS MÚLTIPE. Variante evolutiva a recaídas y remisiones (OMS: 340). Fecha de diagnóstico: Abril/mayo de 1999. Comentarios: Debe continuar sin interrupción, con la terapia inmunomoduladora, con muy buena tolerancia y eficacia hasta la fecha; cuyo objetivo es disminuir el número y la gravedad de las recaídas, así como la cantidad de internaciones y la terapia inmunosupresora más agresiva, retrasando la discapacidad acumulativa y previniendo la atrofia cerebral. Por lo cual se solicita continuidad para Rebif: 3 jeringas prellenadas semanales, es decir 12 jeringas prellenadas de 44Mcgr.=12MUI c/u) c/28 días. Fecha de inicio de Rebif: Septiembre 2004. Por ninguna razón debe discontinuarse su administración pues se correrían riesgos de recaídas con las consecuencias que estas originan (a veces irreparables), debe administrarse hasta que aparezca una terapia superior o efectos adversos insostenibles. Bibliografía respaldatoria: (Rebif) - PRISMS 2 años. Lancet 1998; 352: 1498-1504. - PRISMS 4 años. Neurology 2001; 56: 1628-1636. - INCOMIN Neurology 2001; vol.248: supl.3 / vol.56: supl.2. - OWIMS Neurology 1999; 53: 679-686. - EVIDENCE. Neurology 2002; 59: 1496-1506. - Revista Neurológica Argentina 2000; 25: 142-145. ( - Medicina (Buenos Aires) 2001; 61:470-480. Es un medicamento con cobertura 100% a cargo de la Obra Social, de acuerdo al Boletín Oficial N° 30.089, 1ra. Sección, página 8 del jueves 13 de febrero de 2003 del Plan Médico Obligatorio (o Administración de Programas Especiales) donde Rebif figura expresamente. Se trata además de un medicamento aprobado por la FDA de los EEUU y el ANMAT en la Argentina con esta precisa indicación. Debido a cierta requisitoria quiero dejar bien en claro, sin embargo, que el número de brotes no deben ser limitantes en la provisión de la terapia, dichos criterios simplemente fueron utilizados en los diseños de ensayos terapéuticos y no debieran trasladarse a la clínica diaria sin entender de cada caso particular. Además son criterios de ingreso a la terapia pero de ninguna manera de continuidad de la misma, pues si los brotes se continuarán igual al periodo pre-tratamiento solo reflejarían la ineficacia del mismo, es evidente que existe aun una gran confusión y errónea interpretación de la literatura, además les sugiero remitirse al Consenso Argentino sobre el uso de drogas Inmunomoduladora en EM apartado nº10 que es muy claro al respecto(() y si persistieran aun controversias no dude en comunicarse con este Centro Especializado en Enfermedades Desmielinizantes (único referente del Ministerio de Salud de la Provincia de Bs. As.). Solicito: REBIF (Interferón-B.1ar), a una dosis de12 jeringas prellenadas de 12MUI (44Mcgrs.) c/28días. -UNICA DOSIFICACIÓN POSIBLE- (No existen dos genéricos de este producto por lo que no puede ser cambiado o sustituido por otro nombre comercial distinto al Rebif). Ruego se respete la precisa indicación del médico tratante. Atte. Dr. Santiago A. Vétere ",
    "confidencia": {
      "forma": "Media"
    }
  },
  "validada": {
    "estado": "Procesado",
    "fuente": {
      "tipo": "DOC (Legacy)",
      "nombre_archivo": "historia_20260208_005444_7bff.doc"
    },
    "paciente": {
      "nombre": "Ana Carolina, Battista",
      "dni": null,
      "fecha_nacimiento": "1982-04-02",
      "obra_social": "IOMA",
      "nro_afiliado": "1262506611/01"
    },
    "consulta": {
      "fecha": null,
      "medico": null
    },
    "enfermedad": {
      "diagnostico": "ESCLEROSIS MÚLTIPE. Variante evolutiva a recaídas y remisiones (OMS: 340). Fecha de diagnóstico: Abril/mayo de 1999. Comentarios: Debe continuar sin interrupción, con la terapia inmunomoduladora, con muy buena tolerancia y eficacia hasta la fecha; cuyo objetivo es disminuir el número y la gravedad de las recaídas, así como la cantidad de internaciones y la terapia inmunosupresora más agresiva, retrasando la discapacidad acumulativa y previniendo la atrofia cerebral. Por lo cual se solicita continuidad para Rebif: 3 jeringas prellenadas semanales, es decir 12 jeringas prellenadas de 44Mcgr.=12MUI c/u) c/28 días. Fecha de inicio de Rebif: Septiembre 2004. Por ninguna razón debe discontinuarse su administración pues se correrían riesgos de recaídas con las consecuencias que estas originan (a veces irreparables), debe administrarse hasta que aparezca una terapia superior o efectos adversos insostenibles. Bibliografía respaldatoria: (Rebif) - PRISMS 2 años. Lancet 1998; 352: 1498-1504. - PRISMS 4 años. Neurology 2001; 56: 1628-1636. - INCOMIN Neurology 2001; vol.248: supl.3 / vol.56: supl.2. - OWIMS Neurology 1999; 53: 679-686. - EVIDENCE. Neurology 2002; 59: 1496-1506. - Revista Neurológica Argentina 2000; 25: 142-145. ( - Medicina (Buenos Aires) 2001; 61:470-480. Es un medicamento con cobertura 100% a cargo de la Obra Social, de acuerdo al Boletín Oficial N° 30.089, 1ra. Sección, página 8 del jueves 13 de febrero de 2003 del Plan Médico Obligatorio (o Administración de Programas Especiales) donde Rebif figura expresamente. Se trata además de un medicamento aprobado por la FDA de los EEUU y el ANMAT en la Argentina con esta precisa indicación. Debido a cierta requisitoria quiero dejar bien en claro, sin embargo, que el número de brotes no deben ser limitantes en la provisión de la terapia, dichos criterios simplemente fueron utilizados en los diseños de ensayos terapéuticos y no debieran trasladarse a la clínica diaria sin entender de cada caso particular. Además son criterios de ingreso a la terapia pero de ninguna manera de continuidad de la misma, pues si los brotes se continuarán igual al periodo pre-tratamiento solo reflejarían la ineficacia del mismo, es evidente que existe aun una gran confusión y errónea interpretación de la literatura, además les sugiero remitirse al Consenso Argentino sobre el uso de drogas Inmunomoduladora en EM apartado nº10 que es muy claro al respecto(() y si persistieran aun controversias no dude en comunicarse con este Centro Especializado en Enfermedades Desmielinizantes (único referente del Ministerio de Salud de la Provincia de Bs. As.). Solicito: REBIF (Interferón-B.1ar), a una dosis de12 jeringas prellenadas de 12MUI (44Mcgrs.) c/28días. -UNICA DOSIFICACIÓN POSIBLE- (No existen dos genéricos de este producto por lo que no puede ser cambiado o sustituido por otro nombre comercial distinto al Rebif). Ruego se respete la precisa indicación del médico tratante. Atte. Dr. Santiago A. Vétere",
      "codigo": "G35",
      "forma": "RR",
      "fecha_inicio": "1998-04-02",
      "edss": null
    },
    "complementarios": {
      "rmn": [
        {
          "fecha": null,
          "actividad": null,
          "gd": null,
          "regiones": [
            "periventricular"
          ]
        }
      ],
      "puncion_lumbar": {
        "realizada": false,
        "bandas": null
      }
    },
    "tratamientos": [
      {
        "molecula": "Interferón Beta-1a",
        "droga": "Interferón Beta-1a",
        "dosis": "44 Mcg",
        "frecuencia": "Semanal",
        "estado": "Activo",
        "inicio": null
      },
      {
        "molecula": "Interferón",
        "droga": "Interferón",
        "dosis": "44 Mcg",
        "frecuencia": null,
        "estado": "Activo",
        "inicio": null
      }
    ],
    "secciones_texto": {
      "sintomas_principales": "Obra Social: IOMA Nº de afiliado: 1262506611/01 Inicio de la afección: 2 de abril de 1998 Asistido en este servicio desde: 16 de marzo de 1999 principales: en un curso de brotes y remisiones, múltiples síntomas compatibles con afección de la sustancia blanca del sistema nervioso central, como: parestesias e hipoestesias de miembros, disminución de la fuerza con torpeza motora y dificultades para la marcha, trastornos en el equilibrio y coordinación, fallas en los esfínteres con episódica urgencia urinaria y constipación creciente, compromiso de pares craneanos (segundo, quinto, y sexto par a derecha).Últimas recaídas: -Septiembre 2004: hemiparesia derecha +diplopia; -Enero de 2005: compromiso crural izquierdo leve",
      "antecedentes": "",
      "examen_fisico": "Elementos de: - bipiramidalismo a predominio crural y derecho. - sensitivo-propioceptivo congruente. - atáxico axial y apendicular. - esfinteriano vesical eferente. - pares craneanos: II, V, VI a derecha",
      "agrupacion_sindromica": "",
      "comentario": "Debe continuar sin interrupción, con la terapia inmunomoduladora, con muy buena tolerancia y eficacia hasta la fecha; cuyo objetivo es disminuir el número y la gravedad de las recaídas, así como la cantidad de internaciones y la terapia inmunosupresora más agresiva, retrasando la discapacidad acumulativa y previniendo la atrofia cerebral\nPor lo cual se solicita continuidad para Rebif: 3 jeringas prellenadas semanales, es decir 12 jeringas prellenadas de 44Mcgr.=12MUI c/u) c/28 días\nFecha de inicio de Rebif: Septiembre 2004\nPor ninguna razón debe discontinuarse su administración pues se correrían riesgos de recaídas con las consecuencias que estas originan (a veces irreparables), debe administrarse hasta que aparezca una terapia superior o efectos adversos insostenibles",
      "estudios": "realizados: rutina completa de laboratorio, coagulograma, inmunocolagenograma (factor reumatoide, por RR., y p. de látex; células LE., Ac. anti-nuclares, Ac. anti-ADN y complementemia), determinación de TSH, T3, T4 y Ac. anti-tiroideos, hepatograma completo, serología para VIH, análisis de orina completa\nResultando todos los antes mencionados dentro de parámetros normales\nLas RMN. de cerebro muestran múltiples imágenes en la sustancia blanca del SNC: periventriculares, de extensa topografía, algunas con gran actividad, en el pasado(ver fotocopias de informes que se adjuntan)\nLos potenciales evocados SS. de miembros izquierdos mostraron demora en sus latencias",
      "evolucion": ""
    },
    "texto_original": " HOSPITAL INTERZONAL GENERAL DE AGUDOS “ Gral. SAN MARTIN” SERVICIO DE NEUROLOGÍA SECCIÓN DE ENFERMEDADES DESMIELINIZANTES URGENTE RESUMEN DE HISTORIA CLÍNICA La Plata, . Nombre y apellido: Ana Carolina, Battista. Fecha de Nacimiento: 02/04/82 Dirección: 74 nº 675 Dto. 3. La Plata. Teléfono: 453-5360. Obra Social: IOMA Nº de afiliado: 1262506611/01 Inicio de la afección: 2 de abril de 1998 Asistido en este servicio desde: 16 de marzo de 1999 Síntomas principales: en un curso de brotes y remisiones, múltiples síntomas compatibles con afección de la sustancia blanca del sistema nervioso central, como: parestesias e hipoestesias de miembros, disminución de la fuerza con torpeza motora y dificultades para la marcha, trastornos en el equilibrio y coordinación, fallas en los esfínteres con episódica urgencia urinaria y constipación creciente, compromiso de pares craneanos (segundo, quinto, y sexto par a derecha).Últimas recaídas: -Septiembre 2004: hemiparesia derecha +diplopia; -Enero de 2005: compromiso crural izquierdo leve. Rasgos semiológicos: Elementos de: - bipiramidalismo a predominio crural y derecho. - sensitivo-propioceptivo congruente. - atáxico axial y apendicular. - esfinteriano vesical eferente. - pares craneanos: II, V, VI a derecha. Estudios realizados: rutina completa de laboratorio, coagulograma, inmunocolagenograma (factor reumatoide, por RR., y p. de látex; células LE., Ac. anti-nuclares, Ac. anti-ADN y complementemia), determinación de TSH, T3, T4 y Ac. anti-tiroideos, hepatograma completo, serología para VIH, análisis de orina completa. Resultando todos los antes mencionados dentro de parámetros normales. Las RMN. de cerebro muestran múltiples imágenes en la sustancia blanca del SNC: periventriculares, de extensa topografía, algunas con gran actividad, en el pasado(ver fotocopias de informes que se adjuntan). Los potenciales evocados SS. de miembros izquierdos mostraron demora en sus latencias. Diagnóstico: ESCLEROSIS MÚLTIPE. Variante evolutiva a recaídas y remisiones (OMS: 340). Fecha de diagnóstico: Abril/mayo de 1999. Comentarios: Debe continuar sin interrupción, con la terapia inmunomoduladora, con muy buena tolerancia y eficacia hasta la fecha; cuyo objetivo es disminuir el número y la gravedad de las recaídas, así como la cantidad de internaciones y la terapia inmunosupresora más agresiva, retrasando la discapacidad acumulativa y previniendo la atrofia cerebral. Por lo cual se solicita continuidad para Rebif: 3 jeringas prellenadas semanales, es decir 12 jeringas prellenadas de 44Mcgr.=12MUI c/u) c/28 días. Fecha de inicio de Rebif: Septiembre 2004. Por ninguna razón debe discontinuarse su administración pues se correrían riesgos de recaídas con las consecuencias que estas originan (a veces irreparables), debe administrarse hasta que aparezca una terapia superior o efectos adversos insostenibles. Bibliografía respaldatoria: (Rebif) - PRISMS 2 años. Lancet 1998; 352: 1498-1504. - PRISMS 4 años. Neurology 2001; 56: 1628-1636. - INCOMIN Neurology 2001; vol.248: supl.3 / vol.56: supl.2. - OWIMS Neurology 1999; 53: 679-686. - EVIDENCE. Neurology 2002; 59: 1496-1506. - Revista Neurológica Argentina 2000; 25: 142-145. ( - Medicina (Buenos Aires) 2001; 61:470-480. Es un medicamento con cobertura 100% a cargo de la Obra Social, de acuerdo al Boletín Oficial N° 30.089, 1ra. Sección, página 8 del jueves 13 de febrero de 2003 del Plan Médico Obligatorio (o Administración de Programas Especiales) donde Rebif figura expresamente. Se trata además de un medicamento aprobado por la FDA de los EEUU y el ANMAT en la Argentina con esta precisa indicación. Debido a cierta requisitoria quiero dejar bien en claro, sin embargo, que el número de brotes no deben ser limitantes en la provisión de la terapia, dichos criterios simplemente fueron utilizados en los diseños de ensayos terapéuticos y no debieran trasladarse a la clínica diaria sin entender de cada caso particular. Además son criterios de ingreso a la terapia pero de ninguna manera de continuidad de la misma, pues si los brotes se continuarán igual al periodo pre-tratamiento solo reflejarían la ineficacia del mismo, es evidente que existe aun una gran confusión y errónea interpretación de la literatura, además les sugiero remitirse al Consenso Argentino sobre el uso de drogas Inmunomoduladora en EM apartado nº10 que es muy claro al respecto(() y si persistieran aun controversias no dude en comunicarse con este Centro Especializado en Enfermedades Desmielinizantes (único referente del Ministerio de Salud de la Provincia de Bs. As.). Solicito: REBIF (Interferón-B.1ar), a una dosis de12 jeringas prellenadas de 12MUI (44Mcgrs.) c/28días. -UNICA DOSIFICACIÓN POSIBLE- (No existen dos genéricos de este producto por lo que no puede ser cambiado o sustituido por otro nombre comercial distinto al Rebif). Ruego se respete la precisa indicación del médico tratante. Atte. Dr. Santiago A. Vétere ",
    "confidencia": {
      "forma": "Media"
    }
  },
  "nivel_criticidad": "medio"
}